ifnt/__init__.py
ifnt/random.py
ifnt/testing.py
ifnt/util.py
jax_ifnt-0.1.11.dist-info/licenses/LICENSE
jax_ifnt-0.1.11.dist-info/METADATA
jax_ifnt-0.1.11.dist-info/WHEEL
jax_ifnt-0.1.11.dist-info/top_level.txt
jax_ifnt-0.1.11.dist-info/RECORD
