Metadata-Version: 2.4
Name: jax-ifnt
Version: 0.1.11
Summary: Execute runtime assertions, indexing checks, and more if jax code is not traced.
Requires-Python: >=3.9
License-File: LICENSE
Requires-Dist: jax
Requires-Dist: jaxlib
Dynamic: license-file
